{
    "Ar36": {
        "error": 0.0004133566871679578, 
        "filter_outliers_dict": {
            "filter_outliers": true, 
            "iterations": 1, 
            "std_devs": 2
        }, 
        "fit": "Linear", 
        "value": 0.033983745513890454
    }, 
    "Ar37": {
        "error": 0.010960806774229394, 
        "filter_outliers_dict": {
            "filter_outliers": true, 
            "iterations": 1, 
            "std_devs": 2
        }, 
        "fit": "linear", 
        "value": 5.605364814230612
    }, 
    "Ar38": {
        "error": 0.004940302747322509, 
        "filter_outliers_dict": {
            "filter_outliers": true, 
            "iterations": 1, 
            "std_devs": 2
        }, 
        "fit": "linear", 
        "value": 0.05832196952167688
    }, 
    "Ar39": {
        "error": 0.012161229244606811, 
        "filter_outliers_dict": {
            "filter_outliers": true, 
            "iterations": 1, 
            "std_devs": 2
        }, 
        "fit": "Linear", 
        "value": 1.3671250451727293
    }, 
    "Ar40": {
        "error": 0.022442347857635873, 
        "filter_outliers_dict": {
            "filter_outliers": true, 
            "iterations": 1, 
            "std_devs": 2
        }, 
        "fit": "Linear", 
        "value": 9.718509346392928
    }, 
    "PM41": {
        "error": 0.07502542469755863, 
        "filter_outliers_dict": {
            "filter_outliers": false, 
            "iterations": 1, 
            "std_devs": 2
        }, 
        "fit": "linear", 
        "value": -0.10779551118769815
    }
}