{
    "Ar36": {
        "error": 0.0007146365994558539, 
        "filter_outliers_dict": {
            "filter_outliers": true, 
            "iterations": 1, 
            "std_devs": 2
        }, 
        "fit": "Linear", 
        "value": 0.07542035901594926
    }, 
    "Ar37": {
        "error": 0.017920812471952034, 
        "filter_outliers_dict": {
            "filter_outliers": true, 
            "iterations": 1, 
            "std_devs": 2
        }, 
        "fit": "linear", 
        "value": 53.654095495863885
    }, 
    "Ar38": {
        "error": 0.004749693084463321, 
        "filter_outliers_dict": {
            "filter_outliers": true, 
            "iterations": 1, 
            "std_devs": 2
        }, 
        "fit": "linear", 
        "value": 0.40297778426894065
    }, 
    "Ar39": {
        "error": 0.016710472135188604, 
        "filter_outliers_dict": {
            "filter_outliers": true, 
            "iterations": 1, 
            "std_devs": 2
        }, 
        "fit": "Linear", 
        "value": 31.509659410387705
    }, 
    "Ar40": {
        "error": 0.02324589443367397, 
        "filter_outliers_dict": {
            "filter_outliers": true, 
            "iterations": 1, 
            "std_devs": 2
        }, 
        "fit": "Linear", 
        "value": 142.88659859596987
    }, 
    "PM41": {
        "error": 0.07842268652644971, 
        "filter_outliers_dict": {
            "filter_outliers": false, 
            "iterations": 1, 
            "std_devs": 2
        }, 
        "fit": "linear", 
        "value": -0.1457824925405305
    }
}