{
    "Ar36": {
        "error": 0.0002401637260775985, 
        "filter_outliers_dict": {
            "filter_outliers": true, 
            "iterations": 1, 
            "std_devs": 2
        }, 
        "fit": "Linear", 
        "value": 0.008956871024797213
    }, 
    "Ar37": {
        "error": 0.010816756290839369, 
        "filter_outliers_dict": {
            "filter_outliers": true, 
            "iterations": 1, 
            "std_devs": 2
        }, 
        "fit": "linear", 
        "value": 0.077495521752484
    }, 
    "Ar38": {
        "error": 0.004834484521785214, 
        "filter_outliers_dict": {
            "filter_outliers": true, 
            "iterations": 1, 
            "std_devs": 2
        }, 
        "fit": "linear", 
        "value": 0.19313468353024404
    }, 
    "Ar39": {
        "error": 0.01471773131659356, 
        "filter_outliers_dict": {
            "filter_outliers": true, 
            "iterations": 1, 
            "std_devs": 2
        }, 
        "fit": "Linear", 
        "value": 16.07031758613534
    }, 
    "Ar40": {
        "error": 0.01394502214556276, 
        "filter_outliers_dict": {
            "filter_outliers": true, 
            "iterations": 1, 
            "std_devs": 2
        }, 
        "fit": "Linear", 
        "value": 70.33987657860858
    }, 
    "PM41": {
        "error": 0.0724206818036158, 
        "filter_outliers_dict": {
            "filter_outliers": false, 
            "iterations": 1, 
            "std_devs": 2
        }, 
        "fit": "linear", 
        "value": -0.18559167756664474
    }
}