{
    "Ar36": {
        "error": 0.0003084221416114679, 
        "filter_outliers_dict": {
            "filter_outliers": true, 
            "iterations": 1, 
            "std_devs": 2
        }, 
        "fit": "Linear", 
        "value": 0.013876822350938007
    }, 
    "Ar37": {
        "error": 0.011219391679364074, 
        "filter_outliers_dict": {
            "filter_outliers": true, 
            "iterations": 1, 
            "std_devs": 2
        }, 
        "fit": "linear", 
        "value": 5.058885760042622
    }, 
    "Ar38": {
        "error": 0.004538224828855276, 
        "filter_outliers_dict": {
            "filter_outliers": true, 
            "iterations": 1, 
            "std_devs": 2
        }, 
        "fit": "linear", 
        "value": 0.028049069391894287
    }, 
    "Ar39": {
        "error": 0.011336119014220832, 
        "filter_outliers_dict": {
            "filter_outliers": true, 
            "iterations": 1, 
            "std_devs": 2
        }, 
        "fit": "Linear", 
        "value": 4.004337377834418
    }, 
    "Ar40": {
        "error": 0.010686921355028885, 
        "filter_outliers_dict": {
            "filter_outliers": true, 
            "iterations": 1, 
            "std_devs": 2
        }, 
        "fit": "Linear", 
        "value": 19.029174172945623
    }, 
    "PM41": {
        "error": 0.06706349121163355, 
        "filter_outliers_dict": {
            "filter_outliers": false, 
            "iterations": 1, 
            "std_devs": 2
        }, 
        "fit": "linear", 
        "value": -0.1573530444413725
    }
}