{
    "Ar36": {
        "error": 0.0010369304254555457, 
        "filter_outliers_dict": {
            "filter_outliers": true, 
            "iterations": 1, 
            "std_devs": 2
        }, 
        "fit": "Linear", 
        "value": 0.16425905569177462
    }, 
    "Ar37": {
        "error": 0.010447197333587845, 
        "filter_outliers_dict": {
            "filter_outliers": true, 
            "iterations": 1, 
            "std_devs": 2
        }, 
        "fit": "linear", 
        "value": 1.1677670079381017
    }, 
    "Ar38": {
        "error": 0.006113536643665351, 
        "filter_outliers_dict": {
            "filter_outliers": true, 
            "iterations": 1, 
            "std_devs": 2
        }, 
        "fit": "linear", 
        "value": 0.08277172161466888
    }, 
    "Ar39": {
        "error": 0.012501841366397598, 
        "filter_outliers_dict": {
            "filter_outliers": true, 
            "iterations": 1, 
            "std_devs": 2
        }, 
        "fit": "Linear", 
        "value": 1.540924487402965
    }, 
    "Ar40": {
        "error": 0.01873062126401118, 
        "filter_outliers_dict": {
            "filter_outliers": true, 
            "iterations": 1, 
            "std_devs": 2
        }, 
        "fit": "Linear", 
        "value": 56.58402297305914
    }, 
    "PM41": {
        "error": 0.07733647360794862, 
        "filter_outliers_dict": {
            "filter_outliers": false, 
            "iterations": 1, 
            "std_devs": 2
        }, 
        "fit": "linear", 
        "value": -0.1445354742329427
    }
}