{
    "AX": {
        "error": 0.006433966681534529, 
        "filter_outliers_dict": {
            "filter_outliers": true, 
            "iterations": 1, 
            "std_devs": 2
        }, 
        "fit": "average", 
        "value": -0.08408554105330618
    }, 
    "CDD": {
        "error": 7.2227327769359974e-06, 
        "filter_outliers_dict": {
            "filter_outliers": true, 
            "iterations": 1, 
            "std_devs": 10
        }, 
        "fit": "average", 
        "value": 2.4810901866939498e-05
    }, 
    "H1": {
        "error": 0.004232423744360261, 
        "filter_outliers_dict": {
            "filter_outliers": true, 
            "iterations": 1, 
            "std_devs": 2
        }, 
        "fit": "average", 
        "value": -0.03525052198747615
    }, 
    "H2": {
        "error": 0.008855436945635956, 
        "filter_outliers_dict": {
            "filter_outliers": true, 
            "iterations": 1, 
            "std_devs": 2
        }, 
        "fit": "average", 
        "value": -0.18435002505693918
    }, 
    "L1": {
        "error": 0.0020332022272505925, 
        "filter_outliers_dict": {
            "filter_outliers": true, 
            "iterations": 1, 
            "std_devs": 2
        }, 
        "fit": "average", 
        "value": -0.02358286324697063
    }, 
    "L2": {
        "error": 0.005545675935070209, 
        "filter_outliers_dict": {
            "filter_outliers": true, 
            "iterations": 1, 
            "std_devs": 2
        }, 
        "fit": "average", 
        "value": -0.013165011301948514
    }
}