{
    "AX": {
        "error": 0.005085965361121407, 
        "filter_outliers_dict": {
            "filter_outliers": true, 
            "iterations": 1, 
            "std_devs": 2
        }, 
        "fit": "average", 
        "value": -0.07935310167013232
    }, 
    "CDD": {
        "error": 3.198359786762766e-06, 
        "filter_outliers_dict": {
            "filter_outliers": true, 
            "iterations": 1, 
            "std_devs": 10
        }, 
        "fit": "average", 
        "value": 8.683815653428826e-06
    }, 
    "H1": {
        "error": 0.0035569229859119143, 
        "filter_outliers_dict": {
            "filter_outliers": true, 
            "iterations": 1, 
            "std_devs": 2
        }, 
        "fit": "average", 
        "value": -0.034807407580576544
    }, 
    "H2": {
        "error": 0.0055752474240155035, 
        "filter_outliers_dict": {
            "filter_outliers": true, 
            "iterations": 1, 
            "std_devs": 2
        }, 
        "fit": "average", 
        "value": -0.1815540396116942
    }, 
    "L1": {
        "error": 0.001986406865204213, 
        "filter_outliers_dict": {
            "filter_outliers": true, 
            "iterations": 1, 
            "std_devs": 2
        }, 
        "fit": "average", 
        "value": -0.028346535360432447
    }, 
    "L2": {
        "error": 0.0043583430159121654, 
        "filter_outliers_dict": {
            "filter_outliers": true, 
            "iterations": 1, 
            "std_devs": 2
        }, 
        "fit": "average", 
        "value": -0.01635298348017397
    }
}