{
    "AX": {
        "error": 0.00595091500019495, 
        "filter_outliers_dict": {
            "filter_outliers": true, 
            "iterations": 1, 
            "std_devs": 2
        }, 
        "fit": "average", 
        "value": -0.08626497354631542
    }, 
    "CDD": {
        "error": 1.1890118833345373e-05, 
        "filter_outliers_dict": {
            "filter_outliers": true, 
            "iterations": 1, 
            "std_devs": 10
        }, 
        "fit": "average", 
        "value": 6.202725485664089e-05
    }, 
    "H1": {
        "error": 0.005116024990300357, 
        "filter_outliers_dict": {
            "filter_outliers": true, 
            "iterations": 1, 
            "std_devs": 2
        }, 
        "fit": "average", 
        "value": -0.03641159709197443
    }, 
    "H2": {
        "error": 0.007154016584295313, 
        "filter_outliers_dict": {
            "filter_outliers": true, 
            "iterations": 1, 
            "std_devs": 2
        }, 
        "fit": "average", 
        "value": -0.19530363366617198
    }, 
    "L1": {
        "error": 0.0033302074788532634, 
        "filter_outliers_dict": {
            "filter_outliers": true, 
            "iterations": 1, 
            "std_devs": 2
        }, 
        "fit": "average", 
        "value": -0.027990966353014055
    }, 
    "L2": {
        "error": 0.006593101196956531, 
        "filter_outliers_dict": {
            "filter_outliers": true, 
            "iterations": 1, 
            "std_devs": 2
        }, 
        "fit": "average", 
        "value": -0.016170229017629288
    }
}