{
    "AX": {
        "error": 0.006720644637094447, 
        "filter_outliers_dict": {
            "filter_outliers": true, 
            "iterations": 1, 
            "std_devs": 2
        }, 
        "fit": "average", 
        "value": -0.08026728954413852
    }, 
    "CDD": {
        "error": 7.772412268659315e-06, 
        "filter_outliers_dict": {
            "filter_outliers": true, 
            "iterations": 1, 
            "std_devs": 10
        }, 
        "fit": "average", 
        "value": 2.2329811727568584e-05
    }, 
    "H1": {
        "error": 0.004745354223143327, 
        "filter_outliers_dict": {
            "filter_outliers": true, 
            "iterations": 1, 
            "std_devs": 2
        }, 
        "fit": "average", 
        "value": -0.037384063684623374
    }, 
    "H2": {
        "error": 0.007847546216418819, 
        "filter_outliers_dict": {
            "filter_outliers": true, 
            "iterations": 1, 
            "std_devs": 2
        }, 
        "fit": "average", 
        "value": -0.19334491431141346
    }, 
    "L1": {
        "error": 0.002493264818169516, 
        "filter_outliers_dict": {
            "filter_outliers": true, 
            "iterations": 1, 
            "std_devs": 2
        }, 
        "fit": "average", 
        "value": -0.025039934049778074
    }, 
    "L2": {
        "error": 0.006315322177531976, 
        "filter_outliers_dict": {
            "filter_outliers": true, 
            "iterations": 1, 
            "std_devs": 2
        }, 
        "fit": "average", 
        "value": -0.01876598006530893
    }
}