{
    "AX": {
        "error": 0.004959814161480432, 
        "filter_outliers_dict": {
            "filter_outliers": false, 
            "iterations": 1, 
            "std_devs": 2
        }, 
        "fit": "average_SEM", 
        "value": -0.07640353874011827
    }, 
    "H1": {
        "error": 0.0038022518591579076, 
        "filter_outliers_dict": {
            "filter_outliers": false, 
            "iterations": 1, 
            "std_devs": 2
        }, 
        "fit": "average_SEM", 
        "value": -0.028722774355042436
    }, 
    "L2": {
        "error": 0.00444382751159311, 
        "filter_outliers_dict": {
            "filter_outliers": false, 
            "iterations": 1, 
            "std_devs": 2
        }, 
        "fit": "average_SEM", 
        "value": -0.000911187026402958
    }
}