{
    "Ar36": {
        "error": 0.000311898578748061, 
        "filter_outliers_dict": {
            "filter_outliers": true, 
            "iterations": 1, 
            "std_devs": 2
        }, 
        "fit": "Parabolic", 
        "value": 0.02637607668585182
    }, 
    "Ar37": {
        "error": 0.0049295213974360295, 
        "filter_outliers_dict": {
            "filter_outliers": true, 
            "iterations": 1, 
            "std_devs": 2
        }, 
        "fit": "linear", 
        "value": 0.031122120425494535
    }, 
    "Ar38": {
        "error": 0.002252871274213832, 
        "filter_outliers_dict": {
            "filter_outliers": true, 
            "iterations": 1, 
            "std_devs": 2
        }, 
        "fit": "linear", 
        "value": 0.7927199714099893
    }, 
    "Ar39": {
        "error": 0.012494121517182351, 
        "filter_outliers_dict": {
            "filter_outliers": true, 
            "iterations": 1, 
            "std_devs": 2
        }, 
        "fit": "Parabolic", 
        "value": 62.98356319743935
    }, 
    "Ar40": {
        "error": 0.03439128926523544, 
        "filter_outliers_dict": {
            "filter_outliers": true, 
            "iterations": 1, 
            "std_devs": 2
        }, 
        "fit": "Parabolic", 
        "value": 782.6691064920983
    }, 
    "PM41": {
        "error": 0.06674486610207496, 
        "filter_outliers_dict": {
            "filter_outliers": false, 
            "iterations": 1, 
            "std_devs": 2
        }, 
        "fit": "linear", 
        "value": -0.1526067353665879
    }
}